base_model_tools/__init__.py
base_model_tools/util/__init__.py
base_model_tools/util/models/__init__.py
base_model_tools/util/models/_model.py
base_model_tools/util/models/mlflow.py
base_model_tools/util/models/trainer.py
base_model_tools-1.0.5.dist-info/LICENSE
base_model_tools-1.0.5.dist-info/METADATA
base_model_tools-1.0.5.dist-info/WHEEL
base_model_tools-1.0.5.dist-info/top_level.txt
base_model_tools-1.0.5.dist-info/RECORD
