Metadata-Version: 2.1
Name: base_model_tools
Version: 1.0.5
Summary: Nearly Human Base Model Tools dependency for training, saving, loading, deploying, and inferencing models.
Author: Nearly Human
Author-email: support@nearlyhuman.ai
Keywords: nearlyhuman,nearly human,model,tools
Requires-Python: >=3.8.10
License-File: LICENSE
Requires-Dist: mlflow-skinny>=2.8.0
